ehnpy/__init__.py
ehnpy/actris.py
ehnpy/argo.py
ehnpy/exv.py
ehnpy/functions.py
ehnpy/iagos.py
ehnpy/icos.py
ehnpy/json_cache.py
ehnpy/misc.py
ehnpy/seadatanet.py
tests/test_functions.py
ehnpy-0.1.1.dist-info/METADATA
ehnpy-0.1.1.dist-info/WHEEL
ehnpy-0.1.1.dist-info/top_level.txt
ehnpy-0.1.1.dist-info/RECORD
