Metadata-Version: 2.4
Name: ehnpy
Version: 0.1.1
Summary: A Python package for fetching data from the EnvriHub Next (EHN) project.
Project-URL: Homepage, https://gitlab.a.incd.pt/envri-hub-next/ehnpy
Requires-Python: >=3.7
Requires-Dist: pandas
Requires-Dist: requests
Requires-Dist: jupyter
Requires-Dist: shapely
Requires-Dist: matplotlib
Requires-Dist: pillow
Requires-Dist: argopy
Requires-Dist: numpy
Requires-Dist: cartopy
Requires-Dist: SPARQLWrapper
Requires-Dist: erddapy
Requires-Dist: pyarrow
Requires-Dist: icoscp_core
